llm_code_context/__init__.py
llm_code_context/config_manager.py
llm_code_context/context_generator.py
llm_code_context/file_selector.py
llm_code_context/folder_structure_diagram.py
llm_code_context/templates/full-context.j2
llm_code_context/templates/sel-file-contents.j2
llm_code_context-0.0.9.dist-info/LICENSE
llm_code_context-0.0.9.dist-info/METADATA
llm_code_context-0.0.9.dist-info/WHEEL
llm_code_context-0.0.9.dist-info/entry_points.txt
llm_code_context-0.0.9.dist-info/RECORD
