Metadata-Version: 2.1
Name: llm-code-context
Version: 0.0.9
Summary: A tool to help with copying and pasting context into LLM chats (Deprecated: Renamed to llm-context)
Home-page: https://github.com/cyberchitta/llm-context.py
License: Apache-2.0
Author: restlessronin
Author-email: 88921269+restlessronin@users.noreply.github.com
Requires-Python: >=3.12,<4.0
Classifier: Development Status :: 3 - Alpha
Classifier: Intended Audience :: Developers
Classifier: License :: OSI Approved :: Apache Software License
Classifier: Programming Language :: Python :: 3
Classifier: Programming Language :: Python :: 3.12
Requires-Dist: jinja2 (>=3.1.4,<4.0.0)
Requires-Dist: pathspec (>=0.12.1,<0.13.0)
Requires-Dist: platformdirs (>=4.2.2,<5.0.0)
Requires-Dist: pyperclip (>=1.9.0,<2.0.0)
Project-URL: Repository, https://github.com/cyberchitta/llm-context.py
